{
  "formatid": "gen9randomdoublesbattle",
  "seed": "36,67,98,159",
  "p1Seed": "215,235,265,305",
  "p2Seed": "345,365,405,435",
  "p1TeamPacked": "Blaziken||LifeOrb|SpeedBoost|overheat,stoneedge,closecombat,protect||85,85,85,85,85,85|F|||79|,,,,,Stellar]Malamar||SitrusBerry|Contrary|superpower,knockoff,trickroom,protect||85,85,85,85,85,|F|,,,,,0||80|,,,,,Fighting]Chien-Pao||LifeOrb|SwordofRuin|sacredsword,protect,iciclecrash,suckerpunch||85,85,85,85,85,85|N|||75|,,,,,Ghost]Arceus|ArceusRock|StonePlate|Multitype|judgment,calmmind,fireblast,earthpower||85,,85,85,85,85|N|,0,,,,||73|,,,,,Ground]Terapagos||PowerHerb|TeraShift|terastarstorm,darkpulse,protect,meteorbeam||85,,85,85,85,85|F|,0,,,,||73|,,,,,Stellar]Gogoat||AssaultVest|SapSipper|leafstorm,hornleech,doubleedge,highhorsepower||85,85,85,85,85,85|M|||90|,,,,,Normal",
  "p2TeamPacked": "Brambleghast||LifeOrb|WindRider|shadowsneak,poltergeist,powerwhip,protect||85,85,85,85,85,85|F|||86|,,,,,Water]Electabuzz||Eviolite|Static|followme,thunderbolt,knockoff,electroweb||85,85,85,85,85,85|F|||84|,,,,,Flying]Weavile||LifeOrb|Pickpocket|protect,iceshard,knockoff,tripleaxel||85,85,85,85,85,85|F|||81|,,,,,Dark]Toxicroak||LifeOrb|DrySkin|swordsdance,suckerpunch,closecombat,gunkshot||85,85,85,85,85,85|F|||85|,,,,,Poison]Veluza||ChoiceBand|Sharpness|aquacutter,psychocut,aquajet,nightslash||85,85,85,85,85,85|M|||88|,,,,,Dark]Bombirdier||ChoiceBand|RockyPayload|knockoff,rockslide,bravebird,suckerpunch||85,85,85,85,85,85|F|||84|,,,,,Rock",
  "p1Team": [
    {
      "name": "Blaziken",
      "species": "Blaziken",
      "item": "Life Orb",
      "ability": "Speed Boost",
      "moves": [
        "Overheat",
        "Stone Edge",
        "Close Combat",
        "Protect"
      ],
      "nature": "",
      "evs": {
        "hp": 85,
        "atk": 85,
        "def": 85,
        "spa": 85,
        "spd": 85,
        "spe": 85
      },
      "gender": "F",
      "level": 79,
      "happiness": 255,
      "hpType": "",
      "pokeball": "",
      "gigantamax": false,
      "dynamaxLevel": 10,
      "teraType": "Stellar"
    },
    {
      "name": "Malamar",
      "species": "Malamar",
      "item": "Sitrus Berry",
      "ability": "Contrary",
      "moves": [
        "Superpower",
        "Knock Off",
        "Trick Room",
        "Protect"
      ],
      "nature": "",
      "evs": {
        "hp": 85,
        "atk": 85,
        "def": 85,
        "spa": 85,
        "spd": 85,
        "spe": 0
      },
      "gender": "F",
      "ivs": {
        "hp": 31,
        "atk": 31,
        "def": 31,
        "spa": 31,
        "spd": 31,
        "spe": 0
      },
      "level": 80,
      "happiness": 255,
      "hpType": "",
      "pokeball": "",
      "gigantamax": false,
      "dynamaxLevel": 10,
      "teraType": "Fighting"
    },
    {
      "name": "Chien-Pao",
      "species": "Chien-Pao",
      "item": "Life Orb",
      "ability": "Sword of Ruin",
      "moves": [
        "Sacred Sword",
        "Protect",
        "Icicle Crash",
        "Sucker Punch"
      ],
      "nature": "",
      "evs": {
        "hp": 85,
        "atk": 85,
        "def": 85,
        "spa": 85,
        "spd": 85,
        "spe": 85
      },
      "gender": "N",
      "level": 75,
      "happiness": 255,
      "hpType": "",
      "pokeball": "",
      "gigantamax": false,
      "dynamaxLevel": 10,
      "teraType": "Ghost"
    },
    {
      "name": "Arceus",
      "species": "Arceus-Rock",
      "item": "Stone Plate",
      "ability": "Multitype",
      "moves": [
        "Judgment",
        "Calm Mind",
        "Fire Blast",
        "Earth Power"
      ],
      "nature": "",
      "evs": {
        "hp": 85,
        "atk": 0,
        "def": 85,
        "spa": 85,
        "spd": 85,
        "spe": 85
      },
      "gender": "N",
      "ivs": {
        "hp": 31,
        "atk": 0,
        "def": 31,
        "spa": 31,
        "spd": 31,
        "spe": 31
      },
      "level": 73,
      "happiness": 255,
      "hpType": "",
      "pokeball": "",
      "gigantamax": false,
      "dynamaxLevel": 10,
      "teraType": "Ground"
    },
    {
      "name": "Terapagos",
      "species": "Terapagos",
      "item": "Power Herb",
      "ability": "Tera Shift",
      "moves": [
        "Tera Starstorm",
        "Dark Pulse",
        "Protect",
        "Meteor Beam"
      ],
      "nature": "",
      "evs": {
        "hp": 85,
        "atk": 0,
        "def": 85,
        "spa": 85,
        "spd": 85,
        "spe": 85
      },
      "gender": "F",
      "ivs": {
        "hp": 31,
        "atk": 0,
        "def": 31,
        "spa": 31,
        "spd": 31,
        "spe": 31
      },
      "level": 73,
      "happiness": 255,
      "hpType": "",
      "pokeball": "",
      "gigantamax": false,
      "dynamaxLevel": 10,
      "teraType": "Stellar"
    },
    {
      "name": "Gogoat",
      "species": "Gogoat",
      "item": "Assault Vest",
      "ability": "Sap Sipper",
      "moves": [
        "Leaf Storm",
        "Horn Leech",
        "Double-Edge",
        "High Horsepower"
      ],
      "nature": "",
      "evs": {
        "hp": 85,
        "atk": 85,
        "def": 85,
        "spa": 85,
        "spd": 85,
        "spe": 85
      },
      "gender": "M",
      "level": 90,
      "happiness": 255,
      "hpType": "",
      "pokeball": "",
      "gigantamax": false,
      "dynamaxLevel": 10,
      "teraType": "Normal"
    }
  ],
  "p2Team": [
    {
      "name": "Brambleghast",
      "species": "Brambleghast",
      "item": "Life Orb",
      "ability": "Wind Rider",
      "moves": [
        "Shadow Sneak",
        "Poltergeist",
        "Power Whip",
        "Protect"
      ],
      "nature": "",
      "evs": {
        "hp": 85,
        "atk": 85,
        "def": 85,
        "spa": 85,
        "spd": 85,
        "spe": 85
      },
      "gender": "F",
      "level": 86,
      "happiness": 255,
      "hpType": "",
      "pokeball": "",
      "gigantamax": false,
      "dynamaxLevel": 10,
      "teraType": "Water"
    },
    {
      "name": "Electabuzz",
      "species": "Electabuzz",
      "item": "Eviolite",
      "ability": "Static",
      "moves": [
        "Follow Me",
        "Thunderbolt",
        "Knock Off",
        "Electroweb"
      ],
      "nature": "",
      "evs": {
        "hp": 85,
        "atk": 85,
        "def": 85,
        "spa": 85,
        "spd": 85,
        "spe": 85
      },
      "gender": "F",
      "level": 84,
      "happiness": 255,
      "hpType": "",
      "pokeball": "",
      "gigantamax": false,
      "dynamaxLevel": 10,
      "teraType": "Flying"
    },
    {
      "name": "Weavile",
      "species": "Weavile",
      "item": "Life Orb",
      "ability": "Pickpocket",
      "moves": [
        "Protect",
        "Ice Shard",
        "Knock Off",
        "Triple Axel"
      ],
      "nature": "",
      "evs": {
        "hp": 85,
        "atk": 85,
        "def": 85,
        "spa": 85,
        "spd": 85,
        "spe": 85
      },
      "gender": "F",
      "level": 81,
      "happiness": 255,
      "hpType": "",
      "pokeball": "",
      "gigantamax": false,
      "dynamaxLevel": 10,
      "teraType": "Dark"
    },
    {
      "name": "Toxicroak",
      "species": "Toxicroak",
      "item": "Life Orb",
      "ability": "Dry Skin",
      "moves": [
        "Swords Dance",
        "Sucker Punch",
        "Close Combat",
        "Gunk Shot"
      ],
      "nature": "",
      "evs": {
        "hp": 85,
        "atk": 85,
        "def": 85,
        "spa": 85,
        "spd": 85,
        "spe": 85
      },
      "gender": "F",
      "level": 85,
      "happiness": 255,
      "hpType": "",
      "pokeball": "",
      "gigantamax": false,
      "dynamaxLevel": 10,
      "teraType": "Poison"
    },
    {
      "name": "Veluza",
      "species": "Veluza",
      "item": "Choice Band",
      "ability": "Sharpness",
      "moves": [
        "Aqua Cutter",
        "Psycho Cut",
        "Aqua Jet",
        "Night Slash"
      ],
      "nature": "",
      "evs": {
        "hp": 85,
        "atk": 85,
        "def": 85,
        "spa": 85,
        "spd": 85,
        "spe": 85
      },
      "gender": "M",
      "level": 88,
      "happiness": 255,
      "hpType": "",
      "pokeball": "",
      "gigantamax": false,
      "dynamaxLevel": 10,
      "teraType": "Dark"
    },
    {
      "name": "Bombirdier",
      "species": "Bombirdier",
      "item": "Choice Band",
      "ability": "Rocky Payload",
      "moves": [
        "Knock Off",
        "Rock Slide",
        "Brave Bird",
        "Sucker Punch"
      ],
      "nature": "",
      "evs": {
        "hp": 85,
        "atk": 85,
        "def": 85,
        "spa": 85,
        "spd": 85,
        "spe": 85
      },
      "gender": "F",
      "level": 84,
      "happiness": 255,
      "hpType": "",
      "pokeball": "",
      "gigantamax": false,
      "dynamaxLevel": 10,
      "teraType": "Rock"
    }
  ],
  "inputLog": [
    ">start {\"formatid\":\"gen9randomdoublesbattle\",\"seed\":\"36,67,98,159\"}",
    ">player p1 {\"name\":\"Player1\",\"team\":\"Blaziken||LifeOrb|SpeedBoost|overheat,stoneedge,closecombat,protect||85,85,85,85,85,85|F|||79|,,,,,Stellar]Malamar||SitrusBerry|Contrary|superpower,knockoff,trickroom,protect||85,85,85,85,85,|F|,,,,,0||80|,,,,,Fighting]Chien-Pao||LifeOrb|SwordofRuin|sacredsword,protect,iciclecrash,suckerpunch||85,85,85,85,85,85|N|||75|,,,,,Ghost]Arceus|ArceusRock|StonePlate|Multitype|judgment,calmmind,fireblast,earthpower||85,,85,85,85,85|N|,0,,,,||73|,,,,,Ground]Terapagos||PowerHerb|TeraShift|terastarstorm,darkpulse,protect,meteorbeam||85,,85,85,85,85|F|,0,,,,||73|,,,,,Stellar]Gogoat||AssaultVest|SapSipper|leafstorm,hornleech,doubleedge,highhorsepower||85,85,85,85,85,85|M|||90|,,,,,Normal\"}",
    ">player p2 {\"name\":\"Player2\",\"team\":\"Brambleghast||LifeOrb|WindRider|shadowsneak,poltergeist,powerwhip,protect||85,85,85,85,85,85|F|||86|,,,,,Water]Electabuzz||Eviolite|Static|followme,thunderbolt,knockoff,electroweb||85,85,85,85,85,85|F|||84|,,,,,Flying]Weavile||LifeOrb|Pickpocket|protect,iceshard,knockoff,tripleaxel||85,85,85,85,85,85|F|||81|,,,,,Dark]Toxicroak||LifeOrb|DrySkin|swordsdance,suckerpunch,closecombat,gunkshot||85,85,85,85,85,85|F|||85|,,,,,Poison]Veluza||ChoiceBand|Sharpness|aquacutter,psychocut,aquajet,nightslash||85,85,85,85,85,85|M|||88|,,,,,Dark]Bombirdier||ChoiceBand|RockyPayload|knockoff,rockslide,bravebird,suckerpunch||85,85,85,85,85,85|F|||84|,,,,,Rock\"}",
    ">p1 move stoneedge +2, move protect",
    ">p2 move protect, move knockoff +1",
    ">p1 move protect, move trickroom",
    ">p2 move powerwhip +1, move followme",
    ">p1 move closecombat +2, move trickroom",
    ">p2 move powerwhip +2, move followme",
    ">p1 move overheat +1, move knockoff +2",
    ">p2 move poltergeist +1, move electroweb",
    ">p2 switch 5, switch 6",
    ">p1 move overheat +1, move superpower +2",
    ">p2 move aquacutter +1, move bravebird +2",
    ">p1 switch 4, switch 3",
    ">p1 move judgment +1, move sacredsword +1",
    ">p2 move aquacutter +1, move bravebird +2",
    ">p1 switch 5, switch 6",
    ">p1 move protect, move leafstorm +1",
    ">p2 move aquacutter +1, move bravebird +2",
    ">p1 move meteorbeam +1, pass",
    ">p2 move aquacutter +1, move bravebird +1"
  ]
}