{
  "formatid": "gen9randomdoublesbattle",
  "seed": "99,184,269,438",
  "p1Seed": "584,622,688,782",
  "p2Seed": "876,914,1008,1074",
  "p1TeamPacked": "Mamoswine||LifeOrb|ThickFat|protect,iciclecrash,iceshard,highhorsepower||85,85,85,85,85,85|M|||82|,,,,,Water]Gardevoir||ChoiceSpecs|Trace|psychic,mysticalfire,dazzlinggleam,moonblast||85,,85,85,85,85|F|,0,,,,||83|,,,,,Steel]Lapras||SitrusBerry|WaterAbsorb|icywind,freezedry,protect,muddywater||85,,85,85,85,85|M|,0,,,,||83|,,,,,Ground]Ambipom||SilkScarf|Technician|doubleedge,knockoff,fakeout,protect||85,85,85,85,85,85|F|||87|,,,,,Normal]Slowbro|SlowbroGalar|LifeOrb|Regenerator|shellsidearm,trickroom,fireblast,psychic||85,85,85,85,85,|F|,,,,,0||87|,,,,,Fire]Tentacruel||SitrusBerry|ClearBody|sludgebomb,toxicspikes,hydropump,icywind||85,,85,85,85,85|M|,0,,,,||85|,,,,,Grass",
  "p2TeamPacked": "Deoxys||LifeOrb|Pressure|superpower,psychoboost,extremespeed,protect||85,85,85,85,85,85|N|||79|,,,,,Ghost]Quaquaval||LifeOrb|Moxie|closecombat,protect,tripleaxel,aquastep||85,85,85,85,85,85|F|||82|,,,,,Steel]Polteageist|PolteageistAntique|WhiteHerb|CursedBody|shellsmash,protect,batonpass,shadowball||85,,85,85,85,85|N|,0,,,,||85|,,,,,Normal]Yanmega||LifeOrb|SpeedBoost|airslash,protect,bugbuzz,terablast||85,,85,85,85,85|M|,0,,,,||84|,,,,,Ground]Primarina||ChoiceSpecs|LiquidVoice|flipturn,hypervoice,moonblast,hydropump||85,85,85,85,85,85|M|||79|,,,,,Water]Abomasnow||LightClay|SnowWarning|woodhammer,blizzard,auroraveil,protect||85,85,85,85,85,85|M|||81|,,,,,Ice",
  "p1Team": [
    {
      "name": "Mamoswine",
      "species": "Mamoswine",
      "item": "Life Orb",
      "ability": "Thick Fat",
      "moves": [
        "Protect",
        "Icicle Crash",
        "Ice Shard",
        "High Horsepower"
      ],
      "nature": "",
      "evs": {
        "hp": 85,
        "atk": 85,
        "def": 85,
        "spa": 85,
        "spd": 85,
        "spe": 85
      },
      "gender": "M",
      "level": 82,
      "happiness": 255,
      "hpType": "",
      "pokeball": "",
      "gigantamax": false,
      "dynamaxLevel": 10,
      "teraType": "Water"
    },
    {
      "name": "Gardevoir",
      "species": "Gardevoir",
      "item": "Choice Specs",
      "ability": "Trace",
      "moves": [
        "Psychic",
        "Mystical Fire",
        "Dazzling Gleam",
        "Moonblast"
      ],
      "nature": "",
      "evs": {
        "hp": 85,
        "atk": 0,
        "def": 85,
        "spa": 85,
        "spd": 85,
        "spe": 85
      },
      "gender": "F",
      "ivs": {
        "hp": 31,
        "atk": 0,
        "def": 31,
        "spa": 31,
        "spd": 31,
        "spe": 31
      },
      "level": 83,
      "happiness": 255,
      "hpType": "",
      "pokeball": "",
      "gigantamax": false,
      "dynamaxLevel": 10,
      "teraType": "Steel"
    },
    {
      "name": "Lapras",
      "species": "Lapras",
      "item": "Sitrus Berry",
      "ability": "Water Absorb",
      "moves": [
        "Icy Wind",
        "Freeze-Dry",
        "Protect",
        "Muddy Water"
      ],
      "nature": "",
      "evs": {
        "hp": 85,
        "atk": 0,
        "def": 85,
        "spa": 85,
        "spd": 85,
        "spe": 85
      },
      "gender": "M",
      "ivs": {
        "hp": 31,
        "atk": 0,
        "def": 31,
        "spa": 31,
        "spd": 31,
        "spe": 31
      },
      "level": 83,
      "happiness": 255,
      "hpType": "",
      "pokeball": "",
      "gigantamax": false,
      "dynamaxLevel": 10,
      "teraType": "Ground"
    },
    {
      "name": "Ambipom",
      "species": "Ambipom",
      "item": "Silk Scarf",
      "ability": "Technician",
      "moves": [
        "Double-Edge",
        "Knock Off",
        "Fake Out",
        "Protect"
      ],
      "nature": "",
      "evs": {
        "hp": 85,
        "atk": 85,
        "def": 85,
        "spa": 85,
        "spd": 85,
        "spe": 85
      },
      "gender": "F",
      "level": 87,
      "happiness": 255,
      "hpType": "",
      "pokeball": "",
      "gigantamax": false,
      "dynamaxLevel": 10,
      "teraType": "Normal"
    },
    {
      "name": "Slowbro",
      "species": "Slowbro-Galar",
      "item": "Life Orb",
      "ability": "Regenerator",
      "moves": [
        "Shell Side Arm",
        "Trick Room",
        "Fire Blast",
        "Psychic"
      ],
      "nature": "",
      "evs": {
        "hp": 85,
        "atk": 85,
        "def": 85,
        "spa": 85,
        "spd": 85,
        "spe": 0
      },
      "gender": "F",
      "ivs": {
        "hp": 31,
        "atk": 31,
        "def": 31,
        "spa": 31,
        "spd": 31,
        "spe": 0
      },
      "level": 87,
      "happiness": 255,
      "hpType": "",
      "pokeball": "",
      "gigantamax": false,
      "dynamaxLevel": 10,
      "teraType": "Fire"
    },
    {
      "name": "Tentacruel",
      "species": "Tentacruel",
      "item": "Sitrus Berry",
      "ability": "Clear Body",
      "moves": [
        "Sludge Bomb",
        "Toxic Spikes",
        "Hydro Pump",
        "Icy Wind"
      ],
      "nature": "",
      "evs": {
        "hp": 85,
        "atk": 0,
        "def": 85,
        "spa": 85,
        "spd": 85,
        "spe": 85
      },
      "gender": "M",
      "ivs": {
        "hp": 31,
        "atk": 0,
        "def": 31,
        "spa": 31,
        "spd": 31,
        "spe": 31
      },
      "level": 85,
      "happiness": 255,
      "hpType": "",
      "pokeball": "",
      "gigantamax": false,
      "dynamaxLevel": 10,
      "teraType": "Grass"
    }
  ],
  "p2Team": [
    {
      "name": "Deoxys",
      "species": "Deoxys",
      "item": "Life Orb",
      "ability": "Pressure",
      "moves": [
        "Superpower",
        "Psycho Boost",
        "Extreme Speed",
        "Protect"
      ],
      "nature": "",
      "evs": {
        "hp": 85,
        "atk": 85,
        "def": 85,
        "spa": 85,
        "spd": 85,
        "spe": 85
      },
      "gender": "N",
      "level": 79,
      "happiness": 255,
      "hpType": "",
      "pokeball": "",
      "gigantamax": false,
      "dynamaxLevel": 10,
      "teraType": "Ghost"
    },
    {
      "name": "Quaquaval",
      "species": "Quaquaval",
      "item": "Life Orb",
      "ability": "Moxie",
      "moves": [
        "Close Combat",
        "Protect",
        "Triple Axel",
        "Aqua Step"
      ],
      "nature": "",
      "evs": {
        "hp": 85,
        "atk": 85,
        "def": 85,
        "spa": 85,
        "spd": 85,
        "spe": 85
      },
      "gender": "F",
      "level": 82,
      "happiness": 255,
      "hpType": "",
      "pokeball": "",
      "gigantamax": false,
      "dynamaxLevel": 10,
      "teraType": "Steel"
    },
    {
      "name": "Polteageist",
      "species": "Polteageist-Antique",
      "item": "White Herb",
      "ability": "Cursed Body",
      "moves": [
        "Shell Smash",
        "Protect",
        "Baton Pass",
        "Shadow Ball"
      ],
      "nature": "",
      "evs": {
        "hp": 85,
        "atk": 0,
        "def": 85,
        "spa": 85,
        "spd": 85,
        "spe": 85
      },
      "gender": "N",
      "ivs": {
        "hp": 31,
        "atk": 0,
        "def": 31,
        "spa": 31,
        "spd": 31,
        "spe": 31
      },
      "level": 85,
      "happiness": 255,
      "hpType": "",
      "pokeball": "",
      "gigantamax": false,
      "dynamaxLevel": 10,
      "teraType": "Normal"
    },
    {
      "name": "Yanmega",
      "species": "Yanmega",
      "item": "Life Orb",
      "ability": "Speed Boost",
      "moves": [
        "Air Slash",
        "Protect",
        "Bug Buzz",
        "Tera Blast"
      ],
      "nature": "",
      "evs": {
        "hp": 85,
        "atk": 0,
        "def": 85,
        "spa": 85,
        "spd": 85,
        "spe": 85
      },
      "gender": "M",
      "ivs": {
        "hp": 31,
        "atk": 0,
        "def": 31,
        "spa": 31,
        "spd": 31,
        "spe": 31
      },
      "level": 84,
      "happiness": 255,
      "hpType": "",
      "pokeball": "",
      "gigantamax": false,
      "dynamaxLevel": 10,
      "teraType": "Ground"
    },
    {
      "name": "Primarina",
      "species": "Primarina",
      "item": "Choice Specs",
      "ability": "Liquid Voice",
      "moves": [
        "Flip Turn",
        "Hyper Voice",
        "Moonblast",
        "Hydro Pump"
      ],
      "nature": "",
      "evs": {
        "hp": 85,
        "atk": 85,
        "def": 85,
        "spa": 85,
        "spd": 85,
        "spe": 85
      },
      "gender": "M",
      "level": 79,
      "happiness": 255,
      "hpType": "",
      "pokeball": "",
      "gigantamax": false,
      "dynamaxLevel": 10,
      "teraType": "Water"
    },
    {
      "name": "Abomasnow",
      "species": "Abomasnow",
      "item": "Light Clay",
      "ability": "Snow Warning",
      "moves": [
        "Wood Hammer",
        "Blizzard",
        "Aurora Veil",
        "Protect"
      ],
      "nature": "",
      "evs": {
        "hp": 85,
        "atk": 85,
        "def": 85,
        "spa": 85,
        "spd": 85,
        "spe": 85
      },
      "gender": "M",
      "level": 81,
      "happiness": 255,
      "hpType": "",
      "pokeball": "",
      "gigantamax": false,
      "dynamaxLevel": 10,
      "teraType": "Ice"
    }
  ],
  "inputLog": [
    ">start {\"formatid\":\"gen9randomdoublesbattle\",\"seed\":\"99,184,269,438\"}",
    ">player p1 {\"name\":\"Player1\",\"team\":\"Mamoswine||LifeOrb|ThickFat|protect,iciclecrash,iceshard,highhorsepower||85,85,85,85,85,85|M|||82|,,,,,Water]Gardevoir||ChoiceSpecs|Trace|psychic,mysticalfire,dazzlinggleam,moonblast||85,,85,85,85,85|F|,0,,,,||83|,,,,,Steel]Lapras||SitrusBerry|WaterAbsorb|icywind,freezedry,protect,muddywater||85,,85,85,85,85|M|,0,,,,||83|,,,,,Ground]Ambipom||SilkScarf|Technician|doubleedge,knockoff,fakeout,protect||85,85,85,85,85,85|F|||87|,,,,,Normal]Slowbro|SlowbroGalar|LifeOrb|Regenerator|shellsidearm,trickroom,fireblast,psychic||85,85,85,85,85,|F|,,,,,0||87|,,,,,Fire]Tentacruel||SitrusBerry|ClearBody|sludgebomb,toxicspikes,hydropump,icywind||85,,85,85,85,85|M|,0,,,,||85|,,,,,Grass\"}",
    ">player p2 {\"name\":\"Player2\",\"team\":\"Deoxys||LifeOrb|Pressure|superpower,psychoboost,extremespeed,protect||85,85,85,85,85,85|N|||79|,,,,,Ghost]Quaquaval||LifeOrb|Moxie|closecombat,protect,tripleaxel,aquastep||85,85,85,85,85,85|F|||82|,,,,,Steel]Polteageist|PolteageistAntique|WhiteHerb|CursedBody|shellsmash,protect,batonpass,shadowball||85,,85,85,85,85|N|,0,,,,||85|,,,,,Normal]Yanmega||LifeOrb|SpeedBoost|airslash,protect,bugbuzz,terablast||85,,85,85,85,85|M|,0,,,,||84|,,,,,Ground]Primarina||ChoiceSpecs|LiquidVoice|flipturn,hypervoice,moonblast,hydropump||85,85,85,85,85,85|M|||79|,,,,,Water]Abomasnow||LightClay|SnowWarning|woodhammer,blizzard,auroraveil,protect||85,85,85,85,85,85|M|||81|,,,,,Ice\"}",
    ">p1 move iciclecrash +2, move moonblast +2",
    ">p2 move extremespeed +2, move tripleaxel +1",
    ">p2 switch 4, switch 6",
    ">p1 move iciclecrash +1, move moonblast +1",
    ">p2 move airslash +2, move protect",
    ">p2 switch 3, pass",
    ">p1 move iciclecrash +2, move moonblast +1",
    ">p2 move protect, move auroraveil",
    ">p1 move iciclecrash +2, move moonblast +2",
    ">p2 move shadowball +1, move woodhammer +1",
    ">p1 switch 5, pass",
    ">p1 move shellsidearm +2, move moonblast +2",
    ">p2 move shellsmash, move protect",
    ">p1 move fireblast +2, move moonblast +1",
    ">p2 move shadowball +1, move woodhammer +2",
    ">p1 switch 3, switch 6",
    ">p1 move freezedry +1, move sludgebomb +1",
    ">p2 move batonpass, move blizzard",
    ">p2 switch 5, pass",
    ">p2 switch 5, pass",
    ">p1 move icywind, move icywind",
    ">p2 move protect, move auroraveil",
    ">p1 move freezedry +2, move sludgebomb +1",
    ">p2 move shadowball +2, move blizzard",
    ">p1 move muddywater, move hydropump +1",
    ">p2 move protect, pass",
    ">p1 move icywind, move toxicspikes",
    ">p2 move shadowball +1, pass",
    ">p1 move muddywater, move sludgebomb +1",
    ">p2 move batonpass, pass"
  ]
}